CHANGELOG.txt
LICENCE.txt
MANIFEST.in
README.md
setup.py
endist/__init__.py
endist/main.py
endist/read.py
endist/validation.py
endist.egg-info/PKG-INFO
endist.egg-info/SOURCES.txt
endist.egg-info/dependency_links.txt
endist.egg-info/top_level.txt
endist/forecasting/__init__.py
endist/forecasting/plotting.py
endist/imputation/__init__.py
endist/imputation/plotting.py
endist/preprocessing/__init__.py
endist/preprocessing/features.py
endist/preprocessing/plotting.py
endist/temp_dependency/__init__.py
endist/temp_dependency/plotting.py