Metadata-Version: 2.1
Name: endist
Version: 0.0.3
Summary: A Python library for the distribution system operations
Home-page: UNKNOWN
Author: Blaž Dobravec
License: MIT
Platform: UNKNOWN
Classifier: Development Status :: 5 - Production/Stable
Classifier: Intended Audience :: Developers
Classifier: Operating System :: MacOS :: MacOS X
Classifier: License :: OSI Approved :: MIT License
Classifier: Programming Language :: Python :: 3
Requires-Python: >=3.6
License-File: LICENCE.txt
